lsh23_calculator/__init__.py
lsh23_calculator/calculator.py
lsh23_calculator-0.0.2.dist-info/LICENSE
lsh23_calculator-0.0.2.dist-info/METADATA
lsh23_calculator-0.0.2.dist-info/WHEEL
lsh23_calculator-0.0.2.dist-info/top_level.txt
lsh23_calculator-0.0.2.dist-info/RECORD
