Metadata-Version: 2.1
Name: lsh23-calculator
Version: 0.0.2
Summary: A deploy test package
Author-email: lsh23 <sehyeong.dev@gmail.com>
License: GNU GENERAL PUBLIC LICENSE
Project-URL: Homepage, https://github.com/lsh23/lsh23-calculator
Project-URL: Bug Tracker, https://github.com/lsh23/lsh23-calculator/issues
Classifier: Programming Language :: Python :: 3
Classifier: License :: OSI Approved :: MIT License
Classifier: Operating System :: OS Independent
Requires-Python: >=3.7
License-File: LICENSE
Requires-Dist: pytest
